variable_tracker/__init__.py
variable_tracker/function_tracker.py
variable_tracker/main.py
variable_tracker/models.py
variable_tracker/printer.py
variable_tracker/settings_loader.py
variable_tracker/tracker.py
variable_tracker-0.2.0.dist-info/LICENSE
variable_tracker-0.2.0.dist-info/METADATA
variable_tracker-0.2.0.dist-info/WHEEL
variable_tracker-0.2.0.dist-info/top_level.txt
variable_tracker-0.2.0.dist-info/RECORD
