Metadata-Version: 2.1
Name: variable-tracker
Version: 0.2.0
Summary: A library to globally track variable changes and log them with file, line, and function details.
Author-email: Vimal Mahawar <vimalmahawar1@gmail.com>
License: MIT
Project-URL: Homepage, https://github.com/vimal0207/variable-tracker
Classifier: Programming Language :: Python :: 3
Classifier: License :: OSI Approved :: MIT License
Classifier: Operating System :: OS Independent
Requires-Python: >=3.6
License-File: LICENSE
Requires-Dist: tabulate>=0.9.0
